lbh-0.3.0.dist-info/licenses/LICENSE
llmboost_hub/cli.py
llmboost_hub/commands/attach.py
llmboost_hub/commands/chat.py
llmboost_hub/commands/completions.py
llmboost_hub/commands/fetch.py
llmboost_hub/commands/list.py
llmboost_hub/commands/login.py
llmboost_hub/commands/prep.py
llmboost_hub/commands/run.py
llmboost_hub/commands/serve.py
llmboost_hub/commands/status.py
llmboost_hub/commands/stop.py
llmboost_hub/commands/test_cmd.py
llmboost_hub/commands/tune.py
llmboost_hub/commands/cluster/__init__.py
llmboost_hub/commands/cluster/deploy.py
llmboost_hub/commands/cluster/install.py
llmboost_hub/commands/cluster/logs.py
llmboost_hub/commands/cluster/remove.py
llmboost_hub/commands/cluster/set_docker_config.py
llmboost_hub/commands/cluster/status.py
llmboost_hub/commands/cluster/uninstall.py
llmboost_hub/utils/config.py
llmboost_hub/utils/container_utils.py
llmboost_hub/utils/fs_utils.py
llmboost_hub/utils/gpu_info.py
llmboost_hub/utils/kube_utils.py
llmboost_hub/utils/license_checker.py
llmboost_hub/utils/license_wrapper.py
llmboost_hub/utils/llmboost_version.py
llmboost_hub/utils/lookup_cache.py
llmboost_hub/utils/model_utils.py
llmboost_hub/utils/signature.py
lbh-0.3.0.dist-info/METADATA
lbh-0.3.0.dist-info/WHEEL
lbh-0.3.0.dist-info/entry_points.txt
lbh-0.3.0.dist-info/top_level.txt
lbh-0.3.0.dist-info/RECORD
