Metadata-Version: 2.4
Name: lbh
Version: 0.3.0
Summary: A lightweight CLI tool for managing LLMBoost model images and environments.
Author-email: Harish Kambhampaty <harish.kambhampaty@mangoboost.io>
Project-URL: Homepage, https://github.com/mangoboost/llmboost_hub
Project-URL: Documentation, https://docs.mangoboost.io/llmboost_hub
Project-URL: Source, https://github.com/mangoboost/llmboost_hub
Keywords: LLM,Docker,CLI,HPC,AI,LLMBoost
Classifier: Programming Language :: Python :: 3
Classifier: Operating System :: OS Independent
Classifier: Intended Audience :: Developers
Requires-Python: >=3.11
License-File: LICENSE
Requires-Dist: click>=8.0
Requires-Dist: requests>=2.31
Requires-Dist: openai>=0.27
Requires-Dist: tabulate>=0.9
Requires-Dist: rich>=13.7
Requires-Dist: docker>=7.0
Requires-Dist: pyyaml>=6.0
Requires-Dist: pandas>=2.0
Requires-Dist: licensing
Requires-Dist: bcrypt>=4.0
Requires-Dist: huggingface_hub>=0.23
Requires-Dist: black>=23.1.0
Requires-Dist: cryptography>=41.0
Provides-Extra: dev
Requires-Dist: build>=1.0.0; extra == "dev"
Requires-Dist: wheel>=0.42; extra == "dev"
Requires-Dist: setuptools>=68.0; extra == "dev"
Requires-Dist: twine>=4.0; extra == "dev"
Requires-Dist: nuitka>=2.1; extra == "dev"
Requires-Dist: codeenigma>=1.2; extra == "dev"
Requires-Dist: pytest>=7.4; extra == "dev"
Requires-Dist: pytest-cov>=4.1; extra == "dev"
Requires-Dist: pytest-dependency; extra == "dev"
Requires-Dist: kubernetes==32.0.1; extra == "dev"
Requires-Dist: sh; extra == "dev"
Dynamic: license-file
